metrikflow/__init__.py
metrikflow/cli/__init__.py
metrikflow/cli/base.py
metrikflow/cli/query.py
metrikflow/cli/record.py
metrikflow/cli/commands/__init__.py
metrikflow/cli/commands/query_metric.py
metrikflow/cli/commands/record_metric.py
metrikflow/cli/signals/__init__.py
metrikflow/cli/signals/abort.py
metrikflow/connectors/__init__.py
metrikflow/connectors/async_connector.py
metrikflow/connectors/connector.py
metrikflow/connectors/aws_lambda/__init__.py
metrikflow/connectors/aws_lambda/aws_lambda.py
metrikflow/connectors/aws_lambda/aws_lambda_config.py
metrikflow/connectors/aws_timestream/__init__.py
metrikflow/connectors/aws_timestream/aws_timestream.py
metrikflow/connectors/aws_timestream/aws_timestream_config.py
metrikflow/connectors/aws_timestream/aws_timestream_record.py
metrikflow/connectors/cloudwatch/__init__.py
metrikflow/connectors/cloudwatch/cloudwatch.py
metrikflow/connectors/cloudwatch/cloudwatch_config.py
metrikflow/connectors/common/__init__.py
metrikflow/connectors/common/types.py
metrikflow/connectors/common/signals/__init__.py
metrikflow/connectors/common/signals/add_signal_handler.py
metrikflow/connectors/common/signals/handle_file_stop.py
metrikflow/connectors/common/signals/handle_loop_stop.py
metrikflow/connectors/csv/__init__.py
metrikflow/connectors/csv/csv.py
metrikflow/connectors/csv/csv_config.py
metrikflow/connectors/datadog/__init__.py
metrikflow/connectors/datadog/datadog.py
metrikflow/connectors/datadog/datadog_config.py
metrikflow/connectors/datadog/units/__init__.py
metrikflow/connectors/datadog/units/datadog_unit_map.py
metrikflow/connectors/dogstatsd/__init__.py
metrikflow/connectors/dogstatsd/dogstatsd.py
metrikflow/connectors/dogstatsd/dogstatsd_config.py
metrikflow/connectors/empty/__init__.py
metrikflow/connectors/empty/empty.py
metrikflow/connectors/json/__init__.py
metrikflow/connectors/json/json.py
metrikflow/connectors/json/json_config.py
metrikflow/connectors/kafka/__init__.py
metrikflow/connectors/kafka/kafka.py
metrikflow-0.1.5.dist-info/LICENSE
metrikflow-0.1.5.dist-info/METADATA
metrikflow-0.1.5.dist-info/WHEEL
metrikflow-0.1.5.dist-info/entry_points.txt
metrikflow-0.1.5.dist-info/top_level.txt
metrikflow-0.1.5.dist-info/RECORD
