Metadata-Version: 2.1
Name: metrikflow
Version: 0.1.5
Summary: A library for processing and sending metrics.
Author-email: Ada Lundhe <adalundhe@lundhe.audio>
License: MIT License
Project-URL: Homepage, https://github.com/adalundhe/metrikflow
Keywords: pypi,cicd,python,metrics,datadog,stats,statistics
Classifier: Programming Language :: Python :: 3.10
Classifier: Programming Language :: Python :: 3.11
Classifier: Programming Language :: Python :: 3.12
Classifier: License :: OSI Approved :: MIT License
Classifier: Operating System :: OS Independent
Requires-Python: >=3.10
License-File: LICENSE
Requires-Dist: click
Requires-Dist: psutil
Requires-Dist: aiologger
Requires-Dist: pydantic
Requires-Dist: yaspin
Requires-Dist: art
Requires-Dist: tabulate
Requires-Dist: datadog-api-client
Requires-Dist: aiosonic
